{
  "key": "22T8VYIJ",
  "version": 15746,
  "library": {
    "type": "group",
    "id": 4861694,
    "name": "A Comprehensive Bibliography on Syriac Studies",
    "links": {
      "alternate": {
        "href": "https://www.zotero.org/groups/a_comprehensive_bibliography_on_syriac_studies",
        "type": "text/html"
      }
    }
  },
  "links": {
    "self": {
      "href": "https://api.zotero.org/groups/4861694/items/22T8VYIJ",
      "type": "application/json"
    },
    "alternate": {
      "href": "https://www.zotero.org/groups/a_comprehensive_bibliography_on_syriac_studies/items/22T8VYIJ",
      "type": "text/html"
    }
  },
  "meta": {
    "createdByUser": {
      "id": 8978841,
      "username": "cbss_admin",
      "name": "",
      "links": {
        "alternate": {
          "href": "https://www.zotero.org/cbss_admin",
          "type": "text/html"
        }
      }
    },
    "creatorSummary": "Bornkamm",
    "parsedDate": "1933",
    "numChildren": 0
  },
  "bib": "<div class=\"csl-bib-body\" style=\"line-height: 1.35; padding-left: 1em; text-indent:-1em;\">\n  <div class=\"csl-entry\">Bornkamm, G&#xFC;nther. <i>Mythos und Legende in den apokryphen Thomas-Akten: Beitr&#xE4;ge zur Geschichte der Gnosis und zur Vorgeschichte des Manich&#xE4;ismus</i>. Forschungen zur Religion und Literatur des Alten und Neuen Testaments 49 [NF 31]. G&#xF6;ttingen: Vandenhoeck &amp; Ruprecht, 1933.</div>\n</div>",
  "citation": "<span>G\u00fcnther Bornkamm, <i>Mythos und Legende in den apokryphen Thomas-Akten: Beitr\u00e4ge zur Geschichte der Gnosis und zur Vorgeschichte des Manich\u00e4ismus</i>, Forschungen zur Religion und Literatur des Alten und Neuen Testaments 49 [NF 31] (G\u00f6ttingen: Vandenhoeck &#38; Ruprecht, 1933).</span>",
  "coins": "<span class='Z3988' title='url_ver=Z39.88-2004&amp;ctx_ver=Z39.88-2004&amp;rfr_id=info%3Asid%2Fzotero.org%3A2&amp;rft_val_fmt=info%3Aofi%2Ffmt%3Akev%3Amtx%3Abook&amp;rft.genre=book&amp;rft.btitle=Mythos%20und%20Legende%20in%20den%20apokryphen%20Thomas-Akten%3A%20Beitr%C3%A4ge%20zur%20Geschichte%20der%20Gnosis%20und%20zur%20Vorgeschichte%20des%20Manich%C3%A4ismus&amp;rft.place=G%C3%B6ttingen&amp;rft.publisher=Vandenhoeck%20%26%20Ruprecht&amp;rft.series=Forschungen%20zur%20Religion%20und%20Literatur%20des%20Alten%20und%20Neuen%20Testaments%2049%20%5BNF%2031%5D&amp;rft.aufirst=G%C3%BCnther&amp;rft.aulast=Bornkamm&amp;rft.au=G%C3%BCnther%20Bornkamm&amp;rft.date=1933&amp;rft.language=de'></span>\n",
  "data": {
    "key": "22T8VYIJ",
    "version": 15746,
    "itemType": "book",
    "title": "Mythos und Legende in den apokryphen Thomas-Akten: Beitr\u00e4ge zur Geschichte der Gnosis und zur Vorgeschichte des Manich\u00e4ismus",
    "creators": [
      {
        "creatorType": "author",
        "firstName": "G\u00fcnther",
        "lastName": "Bornkamm"
      }
    ],
    "abstractNote": "",
    "series": "Forschungen zur Religion und Literatur des Alten und Neuen Testaments 49 [NF 31]",
    "seriesNumber": "",
    "volume": "",
    "numberOfVolumes": "",
    "edition": "",
    "place": "G\u00f6ttingen",
    "publisher": "Vandenhoeck & Ruprecht",
    "date": "1933",
    "numPages": "",
    "language": "de",
    "ISBN": "",
    "shortTitle": "",
    "url": "",
    "accessDate": "",
    "archive": "",
    "archiveLocation": "",
    "libraryCatalog": "",
    "callNumber": "",
    "rights": "",
    "extra": "ZoteroURI: https://www.zotero.org/groups/4861694/items/22T8VYIJ\nSyriacaURI: http://syriaca.org/cbss/22T8VYIJ\ndeprecated: http://syriaca.org/bibl/936",
    "tags": [
      {
        "tag": "Acts of Thomas"
      },
      {
        "tag": "Gnosticism"
      },
      {
        "tag": "I-III CE"
      },
      {
        "tag": "Manichaeism"
      },
      {
        "tag": "NT apocrypha"
      },
      {
        "tag": "heterodoxy"
      }
    ],
    "collections": [
      "P4VVZ7P6",
      "YL2LZXJD"
    ],
    "relations": {},
    "dateAdded": "2022-11-18T14:30:53Z",
    "dateModified": "2025-09-17T14:33:50Z"
  }
}