{
  "key": "9D8ZQBIE",
  "version": 16222,
  "library": {
    "type": "group",
    "id": 4861694,
    "name": "A Comprehensive Bibliography on Syriac Studies",
    "links": {
      "alternate": {
        "href": "https://www.zotero.org/groups/a_comprehensive_bibliography_on_syriac_studies",
        "type": "text/html"
      }
    }
  },
  "links": {
    "self": {
      "href": "https://api.zotero.org/groups/4861694/items/9D8ZQBIE",
      "type": "application/json"
    },
    "alternate": {
      "href": "https://www.zotero.org/groups/a_comprehensive_bibliography_on_syriac_studies/items/9D8ZQBIE",
      "type": "text/html"
    }
  },
  "meta": {
    "createdByUser": {
      "id": 8978841,
      "username": "cbss_admin",
      "name": "",
      "links": {
        "alternate": {
          "href": "https://www.zotero.org/cbss_admin",
          "type": "text/html"
        }
      }
    },
    "creatorSummary": "Fransen",
    "parsedDate": "2016",
    "numChildren": 0
  },
  "bib": "<div class=\"csl-bib-body\" style=\"line-height: 1.35; padding-left: 1em; text-indent:-1em;\">\n  <div class=\"csl-entry\">Fransen, Paul-Ir&#xE9;n&#xE9;e. &#x201C;Th&#xE9;odore de Mopsueste sur saint Paul: les fragments de Corbie et le t&#xE9;moignage de Rhaban Maur.&#x201D; <i>Revue B&#xE9;n&#xE9;dictine</i> 126:1 (2016): 112&#x2013;21.</div>\n</div>",
  "citation": "<span>Paul-Ir\u00e9n\u00e9e Fransen, \u201cTh\u00e9odore de Mopsueste sur saint Paul: les fragments de Corbie et le t\u00e9moignage de Rhaban Maur,\u201d <i>Revue B\u00e9n\u00e9dictine</i> 126:1 (2016): 112\u201321.</span>",
  "coins": "<span class='Z3988' title='url_ver=Z39.88-2004&amp;ctx_ver=Z39.88-2004&amp;rfr_id=info%3Asid%2Fzotero.org%3A2&amp;rft_val_fmt=info%3Aofi%2Ffmt%3Akev%3Amtx%3Ajournal&amp;rft.genre=article&amp;rft.atitle=Th%C3%A9odore%20de%20Mopsueste%20sur%20saint%20Paul%3A%20les%20fragments%20de%20Corbie%20et%20le%20t%C3%A9moignage%20de%20Rhaban%20Maur&amp;rft.jtitle=Revue%20B%C3%A9n%C3%A9dictine&amp;rft.volume=126%3A1&amp;rft.aufirst=Paul-Ir%C3%A9n%C3%A9e&amp;rft.aulast=Fransen&amp;rft.au=Paul-Ir%C3%A9n%C3%A9e%20Fransen&amp;rft.date=2016&amp;rft.pages=112-121&amp;rft.spage=112&amp;rft.epage=121&amp;rft.language=fr'></span>\n",
  "data": {
    "key": "9D8ZQBIE",
    "version": 16222,
    "itemType": "journalArticle",
    "title": "Th\u00e9odore de Mopsueste sur saint Paul: les fragments de Corbie et le t\u00e9moignage de Rhaban Maur",
    "creators": [
      {
        "creatorType": "author",
        "firstName": "Paul-Ir\u00e9n\u00e9e",
        "lastName": "Fransen"
      }
    ],
    "abstractNote": "Together with the fragments of Corbie in Paris (CLA, V,++4) of the Commentary of Theodore of Mopsuestia on the Pauline Epistles, described by D. De Bruyne (Rev. b\u00e9n\u00e9d. 33, 1921, p. 53-54), two mutilated Parisian folios and a bifolio in the Vaticana (lat 340 ; now 13501, 59r-60v ; CLA, I,4) must be added. A collation of the whole on the edition of H.B. Swete follows. Rabanus Maurus quotes this commentary according to a composite witness (Theodore and Ambrosiaster). The article proposes an inventary of the quotations of Theodore.",
    "publicationTitle": "Revue B\u00e9n\u00e9dictine",
    "volume": "126:1",
    "issue": "",
    "pages": "112-121",
    "date": "2016",
    "series": "",
    "seriesTitle": "",
    "seriesText": "",
    "journalAbbreviation": "",
    "language": "fr",
    "DOI": "",
    "ISSN": "",
    "shortTitle": "",
    "url": "",
    "accessDate": "",
    "archive": "",
    "archiveLocation": "",
    "libraryCatalog": "",
    "callNumber": "",
    "rights": "",
    "extra": "ZoteroURI: https://www.zotero.org/groups/4861694/items/9D8ZQBIE\nSyriacaURI: http://syriaca.org/cbss/9D8ZQBIE\nCitation Key: Sergey (file)",
    "tags": [
      {
        "tag": "1 Timothy"
      },
      {
        "tag": "2 Timothy"
      },
      {
        "tag": "Antiochene school"
      },
      {
        "tag": "IV-VII CE"
      },
      {
        "tag": "New Testament"
      },
      {
        "tag": "Paul"
      },
      {
        "tag": "Theodore of Mopsuestia"
      },
      {
        "tag": "Titus"
      },
      {
        "tag": "V CE"
      },
      {
        "tag": "commentary"
      },
      {
        "tag": "exegesis"
      }
    ],
    "collections": [
      "P4VVZ7P6",
      "YL2LZXJD"
    ],
    "relations": {},
    "dateAdded": "2022-11-18T14:31:51Z",
    "dateModified": "2025-09-17T18:07:27Z"
  }
}