{
  "key": "9XZ2QIXY",
  "version": 16225,
  "library": {
    "type": "group",
    "id": 4861694,
    "name": "A Comprehensive Bibliography on Syriac Studies",
    "links": {
      "alternate": {
        "href": "https://www.zotero.org/groups/a_comprehensive_bibliography_on_syriac_studies",
        "type": "text/html"
      }
    }
  },
  "links": {
    "self": {
      "href": "https://api.zotero.org/groups/4861694/items/9XZ2QIXY",
      "type": "application/json"
    },
    "alternate": {
      "href": "https://www.zotero.org/groups/a_comprehensive_bibliography_on_syriac_studies/items/9XZ2QIXY",
      "type": "text/html"
    }
  },
  "meta": {
    "createdByUser": {
      "id": 8978841,
      "username": "cbss_admin",
      "name": "",
      "links": {
        "alternate": {
          "href": "https://www.zotero.org/cbss_admin",
          "type": "text/html"
        }
      }
    },
    "creatorSummary": "Freimann",
    "parsedDate": "1892",
    "numChildren": 0
  },
  "bib": "<div class=\"csl-bib-body\" style=\"line-height: 1.35; padding-left: 1em; text-indent:-1em;\">\n  <div class=\"csl-entry\">Freimann, Jacob. <i>Des Gregorius Abulfarag, gen. Bar-Hebr&#xE4;us, Scholien zum Buche Daniel</i>. Beitr&#xE4;ge zum Geschichte der Bibelexegese 1. Br&#xFC;nn: Bernard Epstein, 1892.</div>\n</div>",
  "citation": "<span>Jacob Freimann, <i>Des Gregorius Abulfarag, gen. Bar-Hebr\u00e4us, Scholien zum Buche Daniel</i>, Beitr\u00e4ge zum Geschichte der Bibelexegese 1 (Br\u00fcnn: Bernard Epstein, 1892).</span>",
  "coins": "<span class='Z3988' title='url_ver=Z39.88-2004&amp;ctx_ver=Z39.88-2004&amp;rfr_id=info%3Asid%2Fzotero.org%3A2&amp;rft_val_fmt=info%3Aofi%2Ffmt%3Akev%3Amtx%3Abook&amp;rft.genre=book&amp;rft.btitle=Des%20Gregorius%20Abulfarag%2C%20gen.%20Bar-Hebr%C3%A4us%2C%20Scholien%20zum%20Buche%20Daniel&amp;rft.place=Br%C3%BCnn&amp;rft.publisher=Bernard%20Epstein&amp;rft.series=Beitr%C3%A4ge%20zum%20Geschichte%20der%20Bibelexegese%201&amp;rft.aufirst=Jacob&amp;rft.aulast=Freimann&amp;rft.au=Jacob%20Freimann&amp;rft.date=1892&amp;rft.language=de'></span>\n",
  "data": {
    "key": "9XZ2QIXY",
    "version": 16225,
    "itemType": "book",
    "title": "Des Gregorius Abulfarag, gen. Bar-Hebr\u00e4us, Scholien zum Buche Daniel",
    "creators": [
      {
        "creatorType": "author",
        "firstName": "Jacob",
        "lastName": "Freimann"
      }
    ],
    "abstractNote": "",
    "series": "Beitr\u00e4ge zum Geschichte der Bibelexegese 1",
    "seriesNumber": "",
    "volume": "",
    "numberOfVolumes": "",
    "edition": "",
    "place": "Br\u00fcnn",
    "publisher": "Bernard Epstein",
    "date": "1892",
    "numPages": "",
    "language": "de",
    "ISBN": "",
    "shortTitle": "",
    "url": "",
    "accessDate": "",
    "archive": "",
    "archiveLocation": "",
    "libraryCatalog": "",
    "callNumber": "",
    "rights": "",
    "extra": "ZoteroURI: https://www.zotero.org/groups/4861694/items/9XZ2QIXY\nSyriacaURI: http://syriaca.org/cbss/9XZ2QIXY\nCitation Key: Sergey (file)",
    "tags": [
      {
        "tag": "Barhebraeus"
      },
      {
        "tag": "Daniel"
      },
      {
        "tag": "Jacobites"
      },
      {
        "tag": "Old Testament"
      },
      {
        "tag": "XIII CE"
      },
      {
        "tag": "exegesis"
      },
      {
        "tag": "primary sources [Syriac] + German translation"
      },
      {
        "tag": "scholia"
      }
    ],
    "collections": [
      "P4VVZ7P6",
      "YL2LZXJD"
    ],
    "relations": {},
    "dateAdded": "2022-11-18T14:31:52Z",
    "dateModified": "2025-09-17T18:07:18Z"
  }
}