{
  "key": "B5MXNUER",
  "version": 17526,
  "library": {
    "type": "group",
    "id": 4861694,
    "name": "A Comprehensive Bibliography on Syriac Studies",
    "links": {
      "alternate": {
        "href": "https://www.zotero.org/groups/a_comprehensive_bibliography_on_syriac_studies",
        "type": "text/html"
      }
    }
  },
  "links": {
    "self": {
      "href": "https://api.zotero.org/groups/4861694/items/B5MXNUER",
      "type": "application/json"
    },
    "alternate": {
      "href": "https://www.zotero.org/groups/a_comprehensive_bibliography_on_syriac_studies/items/B5MXNUER",
      "type": "text/html"
    }
  },
  "meta": {
    "createdByUser": {
      "id": 8978841,
      "username": "cbss_admin",
      "name": "",
      "links": {
        "alternate": {
          "href": "https://www.zotero.org/cbss_admin",
          "type": "text/html"
        }
      }
    },
    "creatorSummary": "Tardieu",
    "parsedDate": "2018",
    "numChildren": 0
  },
  "bib": "<div class=\"csl-bib-body\" style=\"line-height: 1.35; padding-left: 1em; text-indent:-1em;\">\n  <div class=\"csl-entry\">Tardieu, Michel. &#x201C;Le Barberousse jacobite de &#x1E24;&#x101;&#x1E25;.&#x201D; In <i>Christianisme des origines: M&#xE9;langes en l&#x2019;honneur du Professeur Paul-Hubert Poirier</i>, edited by Eric Cr&#xE9;gheur, Julio Cesar Dias Chaves, and Steve Johnston, 429&#x2013;36. Juda&#xEF;sme ancien et origines du christianisme 11. Turnhout: Brepols, 2018.</div>\n</div>",
  "citation": "<span>Michel Tardieu, \u201cLe Barberousse jacobite de \u1e24\u0101\u1e25,\u201d in <i>Christianisme des origines: M\u00e9langes en l\u2019honneur du Professeur Paul-Hubert Poirier</i>, ed. Eric Cr\u00e9gheur, Julio Cesar Dias Chaves, and Steve Johnston, Juda\u00efsme ancien et origines du christianisme 11 (Turnhout: Brepols, 2018), 429\u201336.</span>",
  "coins": "<span class='Z3988' title='url_ver=Z39.88-2004&amp;ctx_ver=Z39.88-2004&amp;rfr_id=info%3Asid%2Fzotero.org%3A2&amp;rft_val_fmt=info%3Aofi%2Ffmt%3Akev%3Amtx%3Abook&amp;rft.genre=bookitem&amp;rft.atitle=Le%20Barberousse%20jacobite%20de%20%E1%B8%A4%C4%81%E1%B8%A5&amp;rft.btitle=Christianisme%20des%20origines%3A%20M%C3%A9langes%20en%20l%E2%80%99honneur%20du%20Professeur%20Paul-Hubert%20Poirier&amp;rft.place=Turnhout&amp;rft.publisher=Brepols&amp;rft.series=Juda%C3%AFsme%20ancien%20et%20origines%20du%20christianisme%2011&amp;rft.aufirst=Michel&amp;rft.aulast=Tardieu&amp;rft.au=Michel%20Tardieu&amp;rft.au=Eric%20Cr%C3%A9gheur&amp;rft.au=Julio%20Cesar%20Dias%20Chaves&amp;rft.au=Steve%20Johnston&amp;rft.date=2018&amp;rft.pages=429-436&amp;rft.spage=429&amp;rft.epage=436&amp;rft.language=fr'></span>\n",
  "data": {
    "key": "B5MXNUER",
    "version": 17526,
    "itemType": "bookSection",
    "title": "Le Barberousse jacobite de \u1e24\u0101\u1e25",
    "creators": [
      {
        "creatorType": "author",
        "firstName": "Michel",
        "lastName": "Tardieu"
      },
      {
        "creatorType": "editor",
        "firstName": "Eric",
        "lastName": "Cr\u00e9gheur"
      },
      {
        "creatorType": "editor",
        "firstName": "Julio Cesar",
        "lastName": "Dias Chaves"
      },
      {
        "creatorType": "editor",
        "firstName": "Steve",
        "lastName": "Johnston"
      }
    ],
    "abstractNote": "",
    "bookTitle": "Christianisme des origines: M\u00e9langes en l\u2019honneur du Professeur Paul-Hubert Poirier",
    "series": "Juda\u00efsme ancien et origines du christianisme 11",
    "seriesNumber": "",
    "volume": "",
    "numberOfVolumes": "",
    "edition": "",
    "place": "Turnhout",
    "publisher": "Brepols",
    "date": "2018",
    "pages": "429-436",
    "language": "fr",
    "ISBN": "",
    "shortTitle": "",
    "url": "",
    "accessDate": "",
    "archive": "",
    "archiveLocation": "",
    "libraryCatalog": "",
    "callNumber": "",
    "rights": "",
    "extra": "ZoteroURI: https://www.zotero.org/groups/4861694/items/B5MXNUER\nSyriacaURI: http://syriaca.org/cbss/B5MXNUER\nCitation Key: Sergey (file)",
    "tags": [
      {
        "tag": "Hah"
      },
      {
        "tag": "Jacobites"
      },
      {
        "tag": "Modern Syriac"
      },
      {
        "tag": "Tur Abdin"
      },
      {
        "tag": "XIX-XXI CE"
      },
      {
        "tag": "eschatology"
      },
      {
        "tag": "folklore"
      },
      {
        "tag": "kingship"
      }
    ],
    "collections": [
      "P4VVZ7P6",
      "YL2LZXJD"
    ],
    "relations": {},
    "dateAdded": "2022-11-18T14:35:19Z",
    "dateModified": "2025-09-17T17:14:17Z"
  }
}