{
  "key": "DQFVLCYT",
  "version": 17374,
  "library": {
    "type": "group",
    "id": 4861694,
    "name": "A Comprehensive Bibliography on Syriac Studies",
    "links": {
      "alternate": {
        "href": "https://www.zotero.org/groups/a_comprehensive_bibliography_on_syriac_studies",
        "type": "text/html"
      }
    }
  },
  "links": {
    "self": {
      "href": "https://api.zotero.org/groups/4861694/items/DQFVLCYT",
      "type": "application/json"
    },
    "alternate": {
      "href": "https://www.zotero.org/groups/a_comprehensive_bibliography_on_syriac_studies/items/DQFVLCYT",
      "type": "text/html"
    }
  },
  "meta": {
    "createdByUser": {
      "id": 8978841,
      "username": "cbss_admin",
      "name": "",
      "links": {
        "alternate": {
          "href": "https://www.zotero.org/cbss_admin",
          "type": "text/html"
        }
      }
    },
    "creatorSummary": "Schlimme",
    "parsedDate": "1977",
    "numChildren": 0
  },
  "bib": "<div class=\"csl-bib-body\" style=\"line-height: 1.35; padding-left: 1em; text-indent:-1em;\">\n  <div class=\"csl-entry\">Schlimme, Lorenz. &#x201C;Die Bibelkommentare des Moses bar Kepha.&#x201D; In <i>A Tribute to Arthur V&#xF6;&#xF6;bus: Studies in Early Christian Literature and Its Environment, Primarily in the Syrian East</i>, edited by Robert H. Fischer, 63&#x2013;71. Chicago, Illinois: The Lutheran School of Theology at Chicago, 1977.</div>\n</div>",
  "citation": "<span>Lorenz Schlimme, \u201cDie Bibelkommentare des Moses bar Kepha,\u201d in <i>A Tribute to Arthur V\u00f6\u00f6bus: Studies in Early Christian Literature and Its Environment, Primarily in the Syrian East</i>, ed. Robert H. Fischer (Chicago, Illinois: The Lutheran School of Theology at Chicago, 1977), 63\u201371.</span>",
  "coins": "<span class='Z3988' title='url_ver=Z39.88-2004&amp;ctx_ver=Z39.88-2004&amp;rfr_id=info%3Asid%2Fzotero.org%3A2&amp;rft_val_fmt=info%3Aofi%2Ffmt%3Akev%3Amtx%3Abook&amp;rft.genre=bookitem&amp;rft.atitle=Die%20Bibelkommentare%20des%20Moses%20bar%20Kepha&amp;rft.btitle=A%20Tribute%20to%20Arthur%20V%C3%B6%C3%B6bus%3A%20Studies%20in%20Early%20Christian%20Literature%20and%20Its%20Environment%2C%20Primarily%20in%20the%20Syrian%20East&amp;rft.place=Chicago%2C%20Illinois&amp;rft.publisher=The%20Lutheran%20School%20of%20Theology%20at%20Chicago&amp;rft.aufirst=Lorenz&amp;rft.aulast=Schlimme&amp;rft.au=Lorenz%20Schlimme&amp;rft.au=Robert%20H.%20Fischer&amp;rft.date=1977&amp;rft.pages=63-71&amp;rft.spage=63&amp;rft.epage=71&amp;rft.language=de'></span>\n",
  "data": {
    "key": "DQFVLCYT",
    "version": 17374,
    "itemType": "bookSection",
    "title": "Die Bibelkommentare des Moses bar Kepha",
    "creators": [
      {
        "creatorType": "author",
        "firstName": "Lorenz",
        "lastName": "Schlimme"
      },
      {
        "creatorType": "editor",
        "firstName": "Robert H.",
        "lastName": "Fischer"
      }
    ],
    "abstractNote": "",
    "bookTitle": "A Tribute to Arthur V\u00f6\u00f6bus: Studies in Early Christian Literature and Its Environment, Primarily in the Syrian East",
    "series": "",
    "seriesNumber": "",
    "volume": "",
    "numberOfVolumes": "",
    "edition": "",
    "place": "Chicago, Illinois",
    "publisher": "The Lutheran School of Theology at Chicago",
    "date": "1977",
    "pages": "63-71",
    "language": "de",
    "ISBN": "",
    "shortTitle": "",
    "url": "",
    "accessDate": "",
    "archive": "",
    "archiveLocation": "",
    "libraryCatalog": "",
    "callNumber": "",
    "rights": "",
    "extra": "ZoteroURI: https://www.zotero.org/groups/4861694/items/DQFVLCYT\nSyriacaURI: http://syriaca.org/cbss/DQFVLCYT",
    "tags": [
      {
        "tag": "IX CE"
      },
      {
        "tag": "Moses bar Kepha"
      },
      {
        "tag": "Old Testament"
      },
      {
        "tag": "commentary"
      },
      {
        "tag": "exegesis"
      }
    ],
    "collections": [
      "P4VVZ7P6",
      "YL2LZXJD"
    ],
    "relations": {},
    "dateAdded": "2022-11-18T14:34:52Z",
    "dateModified": "2025-09-17T16:34:26Z"
  }
}