{
  "key": "GT6K5EM7",
  "version": 17701,
  "library": {
    "type": "group",
    "id": 4861694,
    "name": "A Comprehensive Bibliography on Syriac Studies",
    "links": {
      "alternate": {
        "href": "https://www.zotero.org/groups/a_comprehensive_bibliography_on_syriac_studies",
        "type": "text/html"
      }
    }
  },
  "links": {
    "self": {
      "href": "https://api.zotero.org/groups/4861694/items/GT6K5EM7",
      "type": "application/json"
    },
    "alternate": {
      "href": "https://www.zotero.org/groups/a_comprehensive_bibliography_on_syriac_studies/items/GT6K5EM7",
      "type": "text/html"
    }
  },
  "meta": {
    "createdByUser": {
      "id": 8978841,
      "username": "cbss_admin",
      "name": "",
      "links": {
        "alternate": {
          "href": "https://www.zotero.org/cbss_admin",
          "type": "text/html"
        }
      }
    },
    "creatorSummary": "Vleugels",
    "parsedDate": "2010",
    "numChildren": 0
  },
  "bib": "<div class=\"csl-bib-body\" style=\"line-height: 1.35; padding-left: 1em; text-indent:-1em;\">\n  <div class=\"csl-entry\">Vleugels, Gie. <i>De Oden van Salomo: uit het Syrisch vertaald en toegelicht</i>. Bronnen van spiritualiteit. Averbode: Altiora Averbode, 2010.</div>\n</div>",
  "citation": "<span>Gie Vleugels, <i>De Oden van Salomo: uit het Syrisch vertaald en toegelicht</i>, Bronnen van spiritualiteit (Averbode: Altiora Averbode, 2010).</span>",
  "coins": "<span class='Z3988' title='url_ver=Z39.88-2004&amp;ctx_ver=Z39.88-2004&amp;rfr_id=info%3Asid%2Fzotero.org%3A2&amp;rft_val_fmt=info%3Aofi%2Ffmt%3Akev%3Amtx%3Abook&amp;rft.genre=book&amp;rft.btitle=De%20Oden%20van%20Salomo%3A%20uit%20het%20Syrisch%20vertaald%20en%20toegelicht&amp;rft.place=Averbode&amp;rft.publisher=Altiora%20Averbode&amp;rft.series=Bronnen%20van%20spiritualiteit&amp;rft.aufirst=Gie&amp;rft.aulast=Vleugels&amp;rft.au=Gie%20Vleugels&amp;rft.date=2010&amp;rft.language=nl'></span>\n",
  "data": {
    "key": "GT6K5EM7",
    "version": 17701,
    "itemType": "book",
    "title": "De Oden van Salomo: uit het Syrisch vertaald en toegelicht",
    "creators": [
      {
        "creatorType": "author",
        "firstName": "Gie",
        "lastName": "Vleugels"
      }
    ],
    "abstractNote": "",
    "series": "Bronnen van spiritualiteit",
    "seriesNumber": "",
    "volume": "",
    "numberOfVolumes": "",
    "edition": "",
    "place": "Averbode",
    "publisher": "Altiora Averbode",
    "date": "2010",
    "numPages": "",
    "language": "nl",
    "ISBN": "",
    "shortTitle": "",
    "url": "",
    "accessDate": "",
    "archive": "",
    "archiveLocation": "",
    "libraryCatalog": "",
    "callNumber": "",
    "rights": "",
    "extra": "ZoteroURI: https://www.zotero.org/groups/4861694/items/GT6K5EM7\nSyriacaURI: http://syriaca.org/cbss/GT6K5EM7",
    "tags": [
      {
        "tag": "I-III CE"
      },
      {
        "tag": "Odes of Solomon"
      },
      {
        "tag": "hymnography"
      },
      {
        "tag": "poetry"
      },
      {
        "tag": "primary sources [Syriac] - Dutch translation"
      }
    ],
    "collections": [
      "P4VVZ7P6",
      "YL2LZXJD"
    ],
    "relations": {},
    "dateAdded": "2022-11-18T14:35:53Z",
    "dateModified": "2025-09-17T19:03:43Z"
  }
}