{
  "key": "I6L8UJLE",
  "version": 18039,
  "library": {
    "type": "group",
    "id": 4861694,
    "name": "A Comprehensive Bibliography on Syriac Studies",
    "links": {
      "alternate": {
        "href": "https://www.zotero.org/groups/a_comprehensive_bibliography_on_syriac_studies",
        "type": "text/html"
      }
    }
  },
  "links": {
    "self": {
      "href": "https://api.zotero.org/groups/4861694/items/I6L8UJLE",
      "type": "application/json"
    },
    "alternate": {
      "href": "https://www.zotero.org/groups/a_comprehensive_bibliography_on_syriac_studies/items/I6L8UJLE",
      "type": "text/html"
    }
  },
  "meta": {
    "createdByUser": {
      "id": 8978841,
      "username": "cbss_admin",
      "name": "",
      "links": {
        "alternate": {
          "href": "https://www.zotero.org/cbss_admin",
          "type": "text/html"
        }
      }
    },
    "creatorSummary": "Saliba",
    "parsedDate": "2022",
    "numChildren": 0
  },
  "bib": "<div class=\"csl-bib-body\" style=\"line-height: 1.35; padding-left: 1em; text-indent:-1em;\">\n  <div class=\"csl-entry\">Saliba, Saliba. &#x201C;Assemani, le synode du Mont Liban (1736) et la r&#xE9;forme monastique.&#x201D; <i>Parole de l&#x2019;Orient</i> 48 (2022): 183&#x2013;223.</div>\n</div>",
  "citation": "<span>Saliba Saliba, \u201cAssemani, le synode du Mont Liban (1736) et la r\u00e9forme monastique,\u201d <i>Parole de l\u2019Orient</i> 48 (2022): 183\u2013223.</span>",
  "coins": "<span class='Z3988' title='url_ver=Z39.88-2004&amp;ctx_ver=Z39.88-2004&amp;rfr_id=info%3Asid%2Fzotero.org%3A2&amp;rft_val_fmt=info%3Aofi%2Ffmt%3Akev%3Amtx%3Ajournal&amp;rft.genre=article&amp;rft.atitle=Assemani%2C%20le%20synode%20du%20Mont%20Liban%20(1736)%20et%20la%20r%C3%A9forme%20monastique&amp;rft.jtitle=Parole%20de%20l%E2%80%99Orient&amp;rft.volume=48&amp;rft.aufirst=Saliba&amp;rft.aulast=Saliba&amp;rft.au=Saliba%20Saliba&amp;rft.date=2022&amp;rft.pages=183-223&amp;rft.spage=183&amp;rft.epage=223&amp;rft.language=fr'></span>\n",
  "data": {
    "key": "I6L8UJLE",
    "version": 18039,
    "itemType": "journalArticle",
    "title": "Assemani, le synode du Mont Liban (1736) et la r\u00e9forme monastique",
    "creators": [
      {
        "creatorType": "author",
        "firstName": "Saliba",
        "lastName": "Saliba"
      }
    ],
    "abstractNote": "",
    "publicationTitle": "Parole de l\u2019Orient",
    "volume": "48",
    "issue": "",
    "pages": "183-223",
    "date": "2022",
    "series": "",
    "seriesTitle": "",
    "seriesText": "",
    "journalAbbreviation": "",
    "language": "fr",
    "DOI": "",
    "ISSN": "",
    "shortTitle": "",
    "url": "",
    "accessDate": "",
    "archive": "",
    "archiveLocation": "",
    "libraryCatalog": "",
    "callNumber": "",
    "rights": "",
    "extra": "ZoteroURI: https://www.zotero.org/groups/4861694/items/I6L8UJLE\nSyriacaURI: http://syriaca.org/cbss/I6L8UJLE",
    "tags": [
      {
        "tag": "Assemani"
      },
      {
        "tag": "Lebanon"
      },
      {
        "tag": "Maronites"
      },
      {
        "tag": "VII-XVIII CE"
      },
      {
        "tag": "XVIII CE"
      },
      {
        "tag": "councils"
      },
      {
        "tag": "monasticism"
      }
    ],
    "collections": [
      "P4VVZ7P6",
      "TW9XKNJD"
    ],
    "relations": {},
    "dateAdded": "2023-08-18T17:47:28Z",
    "dateModified": "2025-09-17T16:31:09Z"
  }
}