{
  "key": "N2YRTFLS",
  "version": 17375,
  "library": {
    "type": "group",
    "id": 4861694,
    "name": "A Comprehensive Bibliography on Syriac Studies",
    "links": {
      "alternate": {
        "href": "https://www.zotero.org/groups/a_comprehensive_bibliography_on_syriac_studies",
        "type": "text/html"
      }
    }
  },
  "links": {
    "self": {
      "href": "https://api.zotero.org/groups/4861694/items/N2YRTFLS",
      "type": "application/json"
    },
    "alternate": {
      "href": "https://www.zotero.org/groups/a_comprehensive_bibliography_on_syriac_studies/items/N2YRTFLS",
      "type": "text/html"
    }
  },
  "meta": {
    "createdByUser": {
      "id": 8978841,
      "username": "cbss_admin",
      "name": "",
      "links": {
        "alternate": {
          "href": "https://www.zotero.org/cbss_admin",
          "type": "text/html"
        }
      }
    },
    "creatorSummary": "Schmid",
    "parsedDate": "1934",
    "numChildren": 0
  },
  "bib": "<div class=\"csl-bib-body\" style=\"line-height: 1.35; padding-left: 1em; text-indent:-1em;\">\n  <div class=\"csl-entry\">Schmid, Josef. &#x201C;Zus&#xE4;tzliche Bemerkungen.&#x201D; <i>Oriens Christianus</i> III, 9 [31] (1934): 208&#x2013;18.</div>\n</div>",
  "citation": "<span>Josef Schmid, \u201cZus\u00e4tzliche Bemerkungen,\u201d <i>Oriens Christianus</i> III, 9 [31] (1934): 208\u201318.</span>",
  "coins": "<span class='Z3988' title='url_ver=Z39.88-2004&amp;ctx_ver=Z39.88-2004&amp;rfr_id=info%3Asid%2Fzotero.org%3A2&amp;rft_val_fmt=info%3Aofi%2Ffmt%3Akev%3Amtx%3Ajournal&amp;rft.genre=article&amp;rft.atitle=Zus%C3%A4tzliche%20Bemerkungen&amp;rft.jtitle=Oriens%20Christianus&amp;rft.volume=III%2C%209%20%5B31%5D&amp;rft.aufirst=Josef&amp;rft.aulast=Schmid&amp;rft.au=Josef%20Schmid&amp;rft.date=1934&amp;rft.pages=208-218&amp;rft.spage=208&amp;rft.epage=218&amp;rft.language=de'></span>\n",
  "data": {
    "key": "N2YRTFLS",
    "version": 17375,
    "itemType": "journalArticle",
    "title": "Zus\u00e4tzliche Bemerkungen",
    "creators": [
      {
        "creatorType": "author",
        "firstName": "Josef",
        "lastName": "Schmid"
      }
    ],
    "abstractNote": "",
    "publicationTitle": "Oriens Christianus",
    "volume": "III, 9 [31]",
    "issue": "",
    "pages": "208-218",
    "date": "1934",
    "series": "",
    "seriesTitle": "",
    "seriesText": "",
    "journalAbbreviation": "",
    "language": "de",
    "DOI": "",
    "ISSN": "",
    "shortTitle": "",
    "url": "",
    "accessDate": "",
    "archive": "",
    "archiveLocation": "",
    "libraryCatalog": "",
    "callNumber": "",
    "rights": "",
    "extra": "ZoteroURI: https://www.zotero.org/groups/4861694/items/N2YRTFLS\nSyriacaURI: http://syriaca.org/cbss/N2YRTFLS\nCitation Key: Sergey (file)",
    "tags": [
      {
        "tag": "Apocalypse"
      },
      {
        "tag": "Greek Fathers"
      },
      {
        "tag": "IV-VII CE"
      },
      {
        "tag": "Jacobites"
      },
      {
        "tag": "New Testament"
      },
      {
        "tag": "Oecumenius"
      },
      {
        "tag": "commentary"
      },
      {
        "tag": "exegesis"
      },
      {
        "tag": "translations from Greek"
      },
      {
        "tag": "translations into Syriac"
      }
    ],
    "collections": [
      "P4VVZ7P6",
      "YL2LZXJD"
    ],
    "relations": {},
    "dateAdded": "2022-11-18T14:34:52Z",
    "dateModified": "2025-09-17T17:20:22Z"
  }
}