{
  "key": "RVP2I5YM",
  "version": 17026,
  "library": {
    "type": "group",
    "id": 4861694,
    "name": "A Comprehensive Bibliography on Syriac Studies",
    "links": {
      "alternate": {
        "href": "https://www.zotero.org/groups/a_comprehensive_bibliography_on_syriac_studies",
        "type": "text/html"
      }
    }
  },
  "links": {
    "self": {
      "href": "https://api.zotero.org/groups/4861694/items/RVP2I5YM",
      "type": "application/json"
    },
    "alternate": {
      "href": "https://www.zotero.org/groups/a_comprehensive_bibliography_on_syriac_studies/items/RVP2I5YM",
      "type": "text/html"
    }
  },
  "meta": {
    "createdByUser": {
      "id": 8978841,
      "username": "cbss_admin",
      "name": "",
      "links": {
        "alternate": {
          "href": "https://www.zotero.org/cbss_admin",
          "type": "text/html"
        }
      }
    },
    "creatorSummary": "Nau",
    "parsedDate": "1908",
    "numChildren": 0
  },
  "bib": "<div class=\"csl-bib-body\" style=\"line-height: 1.35; padding-left: 1em; text-indent:-1em;\">\n  <div class=\"csl-entry\">Nau, Fran&#xE7;ois. &#x201C;Notes sur diverses hom&#xE9;lies pseud&#xE9;pigraphiques, sur les &#x153;uvres attribu&#xE9;es &#xE0; Eus&#xE8;be d&#x2019;Alexandrie et sur un nouveau manuscrit de la cha&#xEE;ne <i>contra Severianos</i>.&#x201D; <i>Revue de l&#x2019;Orient chr&#xE9;tien</i> II, 3 [13] (1908): 406&#x2013;35.</div>\n</div>",
  "citation": "<span>Fran\u00e7ois Nau, \u201cNotes sur diverses hom\u00e9lies pseud\u00e9pigraphiques, sur les \u0153uvres attribu\u00e9es \u00e0 Eus\u00e8be d\u2019Alexandrie et sur un nouveau manuscrit de la cha\u00eene <i>contra Severianos</i>,\u201d <i>Revue de l\u2019Orient chr\u00e9tien</i> II, 3 [13] (1908): 406\u201335.</span>",
  "coins": "<span class='Z3988' title='url_ver=Z39.88-2004&amp;ctx_ver=Z39.88-2004&amp;rfr_id=info%3Asid%2Fzotero.org%3A2&amp;rft_val_fmt=info%3Aofi%2Ffmt%3Akev%3Amtx%3Ajournal&amp;rft.genre=article&amp;rft.atitle=Notes%20sur%20diverses%20hom%C3%A9lies%20pseud%C3%A9pigraphiques%2C%20sur%20les%20%C5%93uvres%20attribu%C3%A9es%20%C3%A0%20Eus%C3%A8be%20d%E2%80%99Alexandrie%20et%20sur%20un%20nouveau%20manuscrit%20de%20la%20cha%C3%AEne%20%3Ci%3Econtra%20Severianos%3C%2Fi%3E&amp;rft.jtitle=Revue%20de%20l%E2%80%99Orient%20chr%C3%A9tien&amp;rft.volume=II%2C%203%20%5B13%5D&amp;rft.aufirst=Fran%C3%A7ois&amp;rft.aulast=Nau&amp;rft.au=Fran%C3%A7ois%20Nau&amp;rft.date=1908&amp;rft.pages=406-435&amp;rft.spage=406&amp;rft.epage=435&amp;rft.language=fr'></span>\n",
  "data": {
    "key": "RVP2I5YM",
    "version": 17026,
    "itemType": "journalArticle",
    "title": "Notes sur diverses hom\u00e9lies pseud\u00e9pigraphiques, sur les \u0153uvres attribu\u00e9es \u00e0 Eus\u00e8be d\u2019Alexandrie et sur un nouveau manuscrit de la cha\u00eene <i>contra Severianos</i>",
    "creators": [
      {
        "creatorType": "author",
        "firstName": "Fran\u00e7ois",
        "lastName": "Nau"
      }
    ],
    "abstractNote": "",
    "publicationTitle": "Revue de l\u2019Orient chr\u00e9tien",
    "volume": "II, 3 [13]",
    "issue": "",
    "pages": "406-435",
    "date": "1908",
    "series": "",
    "seriesTitle": "",
    "seriesText": "",
    "journalAbbreviation": "",
    "language": "fr",
    "DOI": "",
    "ISSN": "",
    "shortTitle": "",
    "url": "",
    "accessDate": "",
    "archive": "",
    "archiveLocation": "",
    "libraryCatalog": "",
    "callNumber": "",
    "rights": "",
    "extra": "ZoteroURI: https://www.zotero.org/groups/4861694/items/RVP2I5YM\nSyriacaURI: http://syriaca.org/cbss/RVP2I5YM",
    "tags": [
      {
        "tag": "Eusebius of Emesa"
      },
      {
        "tag": "Greek Fathers"
      },
      {
        "tag": "IV CE"
      },
      {
        "tag": "Philoxenus of Mabbug"
      },
      {
        "tag": "primary sources [Syriac] + French translation"
      },
      {
        "tag": "translations from Greek"
      },
      {
        "tag": "translations into Syriac"
      }
    ],
    "collections": [
      "P4VVZ7P6",
      "YL2LZXJD"
    ],
    "relations": {},
    "dateAdded": "2022-11-18T14:33:54Z",
    "dateModified": "2025-09-17T16:07:19Z"
  }
}