{
  "key": "T27QQJSK",
  "version": 18004,
  "library": {
    "type": "group",
    "id": 4861694,
    "name": "A Comprehensive Bibliography on Syriac Studies",
    "links": {
      "alternate": {
        "href": "https://www.zotero.org/groups/a_comprehensive_bibliography_on_syriac_studies",
        "type": "text/html"
      }
    }
  },
  "links": {
    "self": {
      "href": "https://api.zotero.org/groups/4861694/items/T27QQJSK",
      "type": "application/json"
    },
    "alternate": {
      "href": "https://www.zotero.org/groups/a_comprehensive_bibliography_on_syriac_studies/items/T27QQJSK",
      "type": "text/html"
    }
  },
  "meta": {
    "createdByUser": {
      "id": 8978841,
      "username": "cbss_admin",
      "name": "",
      "links": {
        "alternate": {
          "href": "https://www.zotero.org/cbss_admin",
          "type": "text/html"
        }
      }
    },
    "creatorSummary": "Kuhn",
    "parsedDate": "2022",
    "numChildren": 0
  },
  "bib": "<div class=\"csl-bib-body\" style=\"line-height: 1.35; padding-left: 1em; text-indent:-1em;\">\n  <div class=\"csl-entry\">Kuhn, Michael. &#x201C;Ab&#x16B; Al-Faraj Ibn al-&#x1E6C;ayyib (d. 1043): A Scholar-Priest Explains the Trinitarian Persons.&#x201D; In <i>Medieval Encounters: Arabic-Speaking Christians and Islam</i>, edited by Ayman S. Ibrahim, 415&#x2013;52. Gorgias Handbooks 55. Piscataway, New Jersey: Gorgias Press, 2022.</div>\n</div>",
  "citation": "<span>Michael Kuhn, \u201cAb\u016b Al-Faraj Ibn al-\u1e6cayyib (d. 1043): A Scholar-Priest Explains the Trinitarian Persons,\u201d in <i>Medieval Encounters: Arabic-Speaking Christians and Islam</i>, ed. Ayman S. Ibrahim, Gorgias Handbooks 55 (Piscataway, New Jersey: Gorgias Press, 2022), 415\u201352.</span>",
  "coins": "<span class='Z3988' title='url_ver=Z39.88-2004&amp;ctx_ver=Z39.88-2004&amp;rfr_id=info%3Asid%2Fzotero.org%3A2&amp;rft_val_fmt=info%3Aofi%2Ffmt%3Akev%3Amtx%3Abook&amp;rft.genre=bookitem&amp;rft.atitle=Ab%C5%AB%20al-Faraj%20Ibn%20al-%E1%B9%ACayyib%20(d.%201043)%3A%20A%20Scholar-Priest%20Explains%20the%20Trinitarian%20Persons&amp;rft.btitle=Medieval%20Encounters%3A%20Arabic-speaking%20Christians%20and%20Islam&amp;rft.place=Piscataway%2C%20New%20Jersey&amp;rft.publisher=Gorgias%20Press&amp;rft.series=Gorgias%20Handbooks%2055&amp;rft.aufirst=Michael&amp;rft.aulast=Kuhn&amp;rft.au=Michael%20Kuhn&amp;rft.au=Ayman%20S.%20Ibrahim&amp;rft.date=2022&amp;rft.pages=415-452&amp;rft.spage=415&amp;rft.epage=452&amp;rft.language=en'></span>\n",
  "data": {
    "key": "T27QQJSK",
    "version": 18004,
    "itemType": "bookSection",
    "title": "Ab\u016b al-Faraj Ibn al-\u1e6cayyib (d. 1043): A Scholar-Priest Explains the Trinitarian Persons",
    "creators": [
      {
        "creatorType": "author",
        "firstName": "Michael",
        "lastName": "Kuhn"
      },
      {
        "creatorType": "editor",
        "firstName": "Ayman S.",
        "lastName": "Ibrahim"
      }
    ],
    "abstractNote": "",
    "bookTitle": "Medieval Encounters: Arabic-speaking Christians and Islam",
    "series": "Gorgias Handbooks 55",
    "seriesNumber": "",
    "volume": "",
    "numberOfVolumes": "",
    "edition": "",
    "place": "Piscataway, New Jersey",
    "publisher": "Gorgias Press",
    "date": "2022",
    "pages": "415-452",
    "language": "en",
    "ISBN": "",
    "shortTitle": "",
    "url": "",
    "accessDate": "",
    "archive": "",
    "archiveLocation": "",
    "libraryCatalog": "",
    "callNumber": "",
    "rights": "",
    "extra": "ZoteroURI: https://www.zotero.org/groups/4861694/items/T27QQJSK\nSyriacaURI: http://syriaca.org/cbss/T27QQJSK",
    "tags": [
      {
        "tag": "Arab Christians"
      },
      {
        "tag": "Ibn at-Tayyib"
      },
      {
        "tag": "Muslim-Christian relations"
      },
      {
        "tag": "Nestorians"
      },
      {
        "tag": "Trinity"
      },
      {
        "tag": "VII-XVIII CE"
      },
      {
        "tag": "XI CE"
      },
      {
        "tag": "apologetics"
      },
      {
        "tag": "primary sources [Arabic] - English translation"
      }
    ],
    "collections": [
      "P4VVZ7P6",
      "TW9XKNJD"
    ],
    "relations": {},
    "dateAdded": "2023-08-18T17:47:24Z",
    "dateModified": "2025-09-17T15:43:01Z"
  }
}