{
  "key": "XS8FUR5V",
  "version": 17489,
  "library": {
    "type": "group",
    "id": 4861694,
    "name": "A Comprehensive Bibliography on Syriac Studies",
    "links": {
      "alternate": {
        "href": "https://www.zotero.org/groups/a_comprehensive_bibliography_on_syriac_studies",
        "type": "text/html"
      }
    }
  },
  "links": {
    "self": {
      "href": "https://api.zotero.org/groups/4861694/items/XS8FUR5V",
      "type": "application/json"
    },
    "alternate": {
      "href": "https://www.zotero.org/groups/a_comprehensive_bibliography_on_syriac_studies/items/XS8FUR5V",
      "type": "text/html"
    }
  },
  "meta": {
    "createdByUser": {
      "id": 8978841,
      "username": "cbss_admin",
      "name": "",
      "links": {
        "alternate": {
          "href": "https://www.zotero.org/cbss_admin",
          "type": "text/html"
        }
      }
    },
    "creatorSummary": "Swanson",
    "parsedDate": "2013",
    "numChildren": 0
  },
  "bib": "<div class=\"csl-bib-body\" style=\"line-height: 1.35; padding-left: 1em; text-indent:-1em;\">\n  <div class=\"csl-entry\">Swanson, Mark N. &#x201C;D&#x101;niy&#x101;l Al-Sury&#x101;n&#x12B; l-M&#x101;rd&#x12B;n&#x12B;.&#x201D; In <i>Christian-Muslim Relations: A Bibliographical History. Volume 5 (1350&#x2012;1500)</i>, edited by David Richard Thomas and Alex Mallett, 194&#x2013;98. History of Christian-Muslim Relations 20. Leiden: Brill, 2013.</div>\n</div>",
  "citation": "<span>Mark N. Swanson, \u201cD\u0101niy\u0101l Al-Sury\u0101n\u012b l-M\u0101rd\u012bn\u012b,\u201d in <i>Christian-Muslim Relations: A Bibliographical History. Volume 5 (1350\u20121500)</i>, ed. David Richard Thomas and Alex Mallett, History of Christian-Muslim Relations 20 (Leiden: Brill, 2013), 194\u201398.</span>",
  "coins": "<span class='Z3988' title='url_ver=Z39.88-2004&amp;ctx_ver=Z39.88-2004&amp;rfr_id=info%3Asid%2Fzotero.org%3A2&amp;rft_val_fmt=info%3Aofi%2Ffmt%3Akev%3Amtx%3Abook&amp;rft.genre=bookitem&amp;rft.atitle=D%C4%81niy%C4%81l%20al-Sury%C4%81n%C4%AB%20l-M%C4%81rd%C4%ABn%C4%AB&amp;rft.btitle=Christian-Muslim%20Relations%3A%20A%20Bibliographical%20History.%20Volume%205%20(1350%E2%80%921500)&amp;rft.place=Leiden&amp;rft.publisher=Brill&amp;rft.series=History%20of%20Christian-Muslim%20Relations%2020&amp;rft.aufirst=Mark%20N.&amp;rft.aulast=Swanson&amp;rft.au=Mark%20N.%20Swanson&amp;rft.au=David%20Richard%20Thomas&amp;rft.au=Alex%20Mallett&amp;rft.date=2013&amp;rft.pages=194-198&amp;rft.spage=194&amp;rft.epage=198&amp;rft.language=en'></span>\n",
  "data": {
    "key": "XS8FUR5V",
    "version": 17489,
    "itemType": "bookSection",
    "title": "D\u0101niy\u0101l al-Sury\u0101n\u012b l-M\u0101rd\u012bn\u012b",
    "creators": [
      {
        "creatorType": "author",
        "firstName": "Mark N.",
        "lastName": "Swanson"
      },
      {
        "creatorType": "editor",
        "firstName": "David Richard",
        "lastName": "Thomas"
      },
      {
        "creatorType": "editor",
        "firstName": "Alex",
        "lastName": "Mallett"
      }
    ],
    "abstractNote": "",
    "bookTitle": "Christian-Muslim Relations: A Bibliographical History. Volume 5 (1350\u20121500)",
    "series": "History of Christian-Muslim Relations 20",
    "seriesNumber": "",
    "volume": "",
    "numberOfVolumes": "",
    "edition": "",
    "place": "Leiden",
    "publisher": "Brill",
    "date": "2013",
    "pages": "194-198",
    "language": "en",
    "ISBN": "",
    "shortTitle": "",
    "url": "",
    "accessDate": "",
    "archive": "",
    "archiveLocation": "",
    "libraryCatalog": "",
    "callNumber": "",
    "rights": "",
    "extra": "ZoteroURI: https://www.zotero.org/groups/4861694/items/XS8FUR5V\nSyriacaURI: http://syriaca.org/cbss/XS8FUR5V\nCitation Key: Sergey (file)",
    "tags": [
      {
        "tag": "Arab Christians"
      },
      {
        "tag": "Daniel ibn al-Khattab"
      },
      {
        "tag": "Daniel of Mardin"
      },
      {
        "tag": "Jacobites"
      },
      {
        "tag": "Muslim-Christian relations"
      },
      {
        "tag": "VII-XVIII CE"
      },
      {
        "tag": "XIV CE"
      },
      {
        "tag": "apologetics"
      }
    ],
    "collections": [
      "P4VVZ7P6",
      "YL2LZXJD"
    ],
    "relations": {},
    "dateAdded": "2022-11-18T14:35:12Z",
    "dateModified": "2025-09-17T17:15:32Z"
  }
}